<?xml version="1.0" encoding="UTF-8"?>
<?xml-stylesheet type="text/xsl" href="forest.xsl"?><tree expanded="true" show-heading="true" show-metadata="true" toc="false" numbered="false" root="false"><frontmatter><anchor>158</anchor> <taxon>Type Theory</taxon> <addr>cs-0007</addr><route>cs-0007.xml</route>  <date><year>2024</year> <month>3</month> <day>16</day></date>  <title>Categorical Semantics for Type Theories</title>   </frontmatter> <mainmatter><p>
    This is a collection of notes on categorical semantics for type theories.
    The notes are based on the paper by Jason Z.S. Hu.
</p></mainmatter> <backmatter><contributions></contributions> <context></context> <related></related> <backlinks></backlinks> <references></references></backmatter></tree>